statys/__init__.py
statys/core/__init__.py
statys/core/distribution.py
statys/plotters/__init__.py
statys/plotters/critical.py
statys/plotters/significance.py
statys/tests/__init__.py
statys/tests/friedman.py
statys/tests/mann_whitney.py
statys/tests/measure.py
statys/tests/wilcoxon.py
statys/utils/__init__.py
statys/utils/constants.py
statys/utils/exception.py
statys/utils/logging.py
statys/utils/wrappers.py
statys-1.0.1.dist-info/LICENSE
statys-1.0.1.dist-info/METADATA
statys-1.0.1.dist-info/WHEEL
statys-1.0.1.dist-info/top_level.txt
statys-1.0.1.dist-info/RECORD
